flongo_framework/__init__.py
flongo_framework/application.py
flongo_framework/api/__init__.py
flongo_framework/api/errors/__init__.py
flongo_framework/api/errors/request_handling_error.py
flongo_framework/api/errors/schema_validation_error.py
flongo_framework/api/requests/__init__.py
flongo_framework/api/requests/identity.py
flongo_framework/api/requests/request.py
flongo_framework/api/responses/__init__.py
flongo_framework/api/responses/api_json_response.py
flongo_framework/api/responses/api_message_response.py
flongo_framework/api/responses/errors/__init__.py
flongo_framework/api/responses/errors/api_error.py
flongo_framework/api/responses/errors/api_error_message.py
flongo_framework/api/responses/errors/api_error_response.py
flongo_framework/api/routing/__init__.py
flongo_framework/api/routing/route.py
flongo_framework/api/routing/route_permissions.py
flongo_framework/api/routing/route_schema.py
flongo_framework/api/routing/routes.py
flongo_framework/api/routing/handlers/__init__.py
flongo_framework/api/routing/handlers/default_route_handler.py
flongo_framework/api/routing/handlers/route_handler.py
flongo_framework/api/routing/utils/__init__.py
flongo_framework/api/routing/utils/authentication_util.py
flongo_framework/api/routing/utils/tranformers/__init__.py
flongo_framework/api/routing/utils/tranformers/field_transformer.py
flongo_framework/api/routing/utils/tranformers/route_transformer.py
flongo_framework/config/__init__.py
flongo_framework/config/enums/__init__.py
flongo_framework/config/enums/environments.py
flongo_framework/config/enums/http_methods.py
flongo_framework/config/enums/mongodb_index_types.py
flongo_framework/config/enums/base/__init__.py
flongo_framework/config/enums/base/base_enum.py
flongo_framework/config/enums/base/base_str_enum.py
flongo_framework/config/enums/logs/__init__.py
flongo_framework/config/enums/logs/log_groups.py
flongo_framework/config/enums/logs/log_levels.py
flongo_framework/config/enums/logs/colors/__init__.py
flongo_framework-0.4.0.dist-info/LICENSE
flongo_framework-0.4.0.dist-info/METADATA
flongo_framework-0.4.0.dist-info/WHEEL
flongo_framework-0.4.0.dist-info/top_level.txt
flongo_framework-0.4.0.dist-info/RECORD
