Metadata-Version: 2.1
Name: flongo-framework
Version: 0.4.0
Summary: Flask framework with out of the box Logging, MongoDB, JWT, CORs, Sentry and Docker support
Home-page: https://github.com/Topazoo/Flongo-Framework
Author: Peter Swanson
Author-email: pswanson@ucdavis.edu
License: LICENSE
Platform: UNKNOWN
Requires-Python: >=3.9
License-File: LICENSE
Requires-Dist: Query-String-Manager>=1.0.11
Requires-Dist: gmail-python-client>=0.0.4
Requires-Dist: Flask==3.0.0
Requires-Dist: pyopenssl==23.2.0
Requires-Dist: pymongo[srv]==4.5.0
Requires-Dist: xmltodict>=0.13.0
Requires-Dist: flask-cors==4.0.0
Requires-Dist: Flask-JWT-Extended==4.5.3
Requires-Dist: sentry-sdk[flask]>=1.32.0
Requires-Dist: gunicorn>=21.2.0
Requires-Dist: jsonschema>=4.19.1
Requires-Dist: bcrypt>=4.0.1
